gmcli/__init__.py
gmcli/main.py
gmcli/models/GaijinMarket.py
gmcli/models/Item.py
gmcli/models/Receipt.py
gmcli/models/User.py
gmcli/models/__init__.py
gmcli-0.0.1.dist-info/METADATA
gmcli-0.0.1.dist-info/WHEEL
gmcli-0.0.1.dist-info/entry_points.txt
gmcli-0.0.1.dist-info/top_level.txt
gmcli-0.0.1.dist-info/RECORD
