Metadata-Version: 2.1
Name: gmcli
Version: 0.0.1
Summary: CLI to interact with the Gaijin Market.
Home-page: https://github.com/JowiAoun/Gaijin-Market-CLI
Author: Jowi Aoun
Requires-Dist: click
Requires-Dist: python-dotenv
